convert/__init__.py
convert/print_convert.py
flex_util-0.0.1.dist-info/METADATA
flex_util-0.0.1.dist-info/WHEEL
flex_util-0.0.1.dist-info/top_level.txt
flex_util-0.0.1.dist-info/RECORD
